ovos_ww_plugin_pocketsphinx/__init__.py
ovos_ww_plugin_pocketsphinx/version.py
ovos_ww_plugin_pocketsphinx-0.1.4.dist-info/LICENSE
ovos_ww_plugin_pocketsphinx-0.1.4.dist-info/METADATA
ovos_ww_plugin_pocketsphinx-0.1.4.dist-info/WHEEL
ovos_ww_plugin_pocketsphinx-0.1.4.dist-info/entry_points.txt
ovos_ww_plugin_pocketsphinx-0.1.4.dist-info/top_level.txt
ovos_ww_plugin_pocketsphinx-0.1.4.dist-info/zip-safe
ovos_ww_plugin_pocketsphinx-0.1.4.dist-info/RECORD
