Metadata-Version: 2.1
Name: ovos-ww-plugin-pocketsphinx
Version: 0.1.4
Summary: A wake word plugin for OpenVoiceOS
Home-page: https://github.com/OpenVoiceOS/ovos-ww-plugin-pocketsphinx
Author: JarbasAi
Author-email: jarbasai@mailfence.com
License: Apache-2.0
Keywords: mycroft ovos plugin wake word
Platform: UNKNOWN
Classifier: Development Status :: 3 - Alpha
Classifier: Intended Audience :: Developers
Classifier: Topic :: Text Processing :: Linguistic
Classifier: License :: OSI Approved :: Apache Software License
Classifier: Programming Language :: Python :: 2
Classifier: Programming Language :: Python :: 2.7
Classifier: Programming Language :: Python :: 3
Classifier: Programming Language :: Python :: 3.0
Classifier: Programming Language :: Python :: 3.1
Classifier: Programming Language :: Python :: 3.2
Classifier: Programming Language :: Python :: 3.3
Classifier: Programming Language :: Python :: 3.4
Classifier: Programming Language :: Python :: 3.5
Classifier: Programming Language :: Python :: 3.6
Requires-Dist: pocketsphinx~=0.1
Requires-Dist: ovos-plugin-manager>=0.0.1
Requires-Dist: phoneme-guesser~=0.1.1
Requires-Dist: SpeechRecognition>=3.8.1
